MANIFEST.in
README.md
setup.cfg
setup.py
test_comp.sh
src/img2pdf.py
src/jp2.py
src/img2pdf_legacy_python.egg-info/PKG-INFO
src/img2pdf_legacy_python.egg-info/SOURCES.txt
src/img2pdf_legacy_python.egg-info/dependency_links.txt
src/img2pdf_legacy_python.egg-info/entry_points.txt
src/img2pdf_legacy_python.egg-info/requires.txt
src/img2pdf_legacy_python.egg-info/top_level.txt
src/img2pdf_legacy_python.egg-info/zip-safe
src/tests/__init__.py
src/tests/input/CMYK.jpg
src/tests/input/mono.png
src/tests/input/normal.jpg
src/tests/input/normal.png
src/tests/output/CMYK.jpg.pdf
src/tests/output/CMYK.tif.pdf
src/tests/output/mono.png.pdf
src/tests/output/normal.jpg.pdf
src/tests/output/normal.png.pdf