Metadata-Version: 1.1
Name: img2pdf-legacy-python
Version: 0.2.3
Summary: Python 2-compatible fork of img2pdf
Home-page: https://github.com/lucaswiman/img2pdf-legacy-python
Author: Lucas Wiman (fork); Johannes 'josch' Schauer (original author)
Author-email: lucas.wiman@gmail.com
License: LGPL
Keywords: jpeg pdf converter
Platform: UNKNOWN
Classifier: Development Status :: 5 - Production/Stable
Classifier: Intended Audience :: Developers
Classifier: Intended Audience :: Other Audience
Classifier: Environment :: Console
Classifier: Programming Language :: Python
Classifier: Programming Language :: Python :: 2
Classifier: Programming Language :: Python :: 2.7
Classifier: Programming Language :: Python :: Implementation :: CPython
Classifier: License :: OSI Approved :: GNU Lesser General Public License v3 (LGPLv3)
Classifier: Natural Language :: English
Classifier: Operating System :: OS Independent
